README.md
setup.py
glooweb/__init__.py
glooweb/_struct.py
glooweb/route.py
glooweb/view.py
glooweb/web.py
glooweb.egg-info/PKG-INFO
glooweb.egg-info/SOURCES.txt
glooweb.egg-info/dependency_links.txt
glooweb.egg-info/requires.txt
glooweb.egg-info/top_level.txt
test/test1.py
test/test2.py