Metadata-Version: 2.1
Name: glooweb
Version: 0.1.7
Summary: Simple web framework based on WSGI protocol
Home-page: UNKNOWN
Author: gloo
Author-email: gloo.luo@foxmail.com
License: UNKNOWN
Keywords: api,web
Platform: UNKNOWN
